color.py
install.py
pySSL.py
pyssl/__init__.py
pyssl/_makecode.pyd
pyssl/_pyssl.pyd
pythonssl-0.0.3a5.dist-info/METADATA
pythonssl-0.0.3a5.dist-info/WHEEL
pythonssl-0.0.3a5.dist-info/top_level.txt
pythonssl-0.0.3a5.dist-info/RECORD
