Metadata-Version: 2.1
Name: pythonssl
Version: 0.0.3a5
Summary: Create a certificate file and a private key file in x509 framework.
Home-page: https://github.com/phucbao9x/pyssl
Download-URL: https://sourceforge.net/projects/pythonssl/files/pythonssl-0.0.3a5-py3-none-any.whl/download
Author: Phuc Bao
Author-email: kaioffrayce@gmail.com
Requires-Dist: cryptography
